gentopo/__about__.py
gentopo/__init__.py
gentopo/__main__.py
gentopo/cli/__init__.py
gentopo/topology/generate.py
gentopo/topology/utils.py
gentopo/topology/validate_config.py
gentopo/topology/families/__init__.py
gentopo/topology/families/complete.py
gentopo/topology/families/lattice.py
gentopo/topology/families/random.py
gentopo/topology/families/small_world.py
gentopo-0.0.1.dist-info/METADATA
gentopo-0.0.1.dist-info/WHEEL
gentopo-0.0.1.dist-info/licenses/LICENSE
gentopo-0.0.1.dist-info/RECORD
