Metadata-Version: 2.1
Name: gentopo
Version: 0.0.1
Summary: Generate network topologies and underlying sequences of interactions that lead to them.
Project-URL: Homepage, https://github.com/comanlab/gentopo
Project-URL: Repository, https://github.com/comanlab/gentopo.git
Author-email: Ari Dyckovsky <aridyckovsky@gmail.com>
Maintainer-email: Ari Dyckovsky <aridyckovsky@gmail.com>
License-Expression: MIT
License-File: LICENSE
Keywords: interaction,networks,social science,topology
Classifier: Programming Language :: Python
Requires-Python: >=3.10
Requires-Dist: click
Requires-Dist: networkx==3.2.1
Requires-Dist: numpy==1.26.2
